PySharer/FILE_TYPES.py
PySharer/__init__.py
PySharer/run.py
PySharer/version.py
PySharer/static/css/style.css
PySharer/static/img/audio.png
PySharer/static/img/css.png
PySharer/static/img/db.png
PySharer/static/img/dir.png
PySharer/static/img/drive.png
PySharer/static/img/excel.png
PySharer/static/img/exe.png
PySharer/static/img/html.png
PySharer/static/img/image.png
PySharer/static/img/js.png
PySharer/static/img/parent_dir.png
PySharer/static/img/pdf.png
PySharer/static/img/powerpoint.png
PySharer/static/img/py.png
PySharer/static/img/qrCode.png
PySharer/static/img/short_logo.png
PySharer/static/img/short_logo_1.png
PySharer/static/img/text.png
PySharer/static/img/unknown.png
PySharer/static/img/upload.png
PySharer/static/img/video.png
PySharer/static/img/word.png
PySharer/static/img/zip.png
PySharer/static/javascript/app.js
PySharer/static/javascript/qrcode.min.js
PySharer/templates/index.html
PySharer-1.2.0.dist-info/LICENSE
PySharer-1.2.0.dist-info/METADATA
PySharer-1.2.0.dist-info/WHEEL
PySharer-1.2.0.dist-info/entry_points.txt
PySharer-1.2.0.dist-info/top_level.txt
PySharer-1.2.0.dist-info/RECORD
