Metadata-Version: 2.1
Name: PySharer
Version: 1.2.0
Summary: PySharer is a Flask-based web application for sharing files using LAN.
Home-page: https://github.com/Mr-Bilal-Ashraf/PySharer
Author: Muhammad Bilal Azaad
Author-email: mr.bilal2066@gmail.com
License: MIT
Classifier: Programming Language :: Python :: 3
Classifier: License :: OSI Approved :: MIT License
Classifier: Operating System :: OS Independent
Classifier: Framework :: Flask
Requires-Python: >=3.7
License-File: LICENSE
Requires-Dist: Flask>=2.0.0
Requires-Dist: Werkzeug>=2.0.0
